{
	"info": {
	  "name": "Ward 21 - Alderman",
	  "date": "2022-08-02",
	  "jurisdictionPath": "us/mo/stl",
	  "electionPath": "2022/08",
	  "office": "wd22",
	  "officeName": "Ward 21 - Alderman",
	  "jurisdictionName": "St Louis, MO",
	  "electionName": "Special Primary Election",
	  "website": "https://www.stlouis-mo.gov/government/departments/board-election-commissioners/documents/election-results/upload/Aug22-Wd21-Final-Official-Summary.pdf"
	},
	"ballotCount": 1195,
	"candidates": [
	  {
	    "name": "Laura Keys",
	    "candidate_type": "Regular",
	    "votes": 671,
	    "winner": true
	  },
	  {
	    "name": "Joann Williams",
	    "candidate_type": "Regular",
	    "votes": 376,
	    "winner": true
	  },
	  {
	    "name": "Melinda Long",
	    "candidate_type": "Regular",
	    "votes": 97,
	    "winner": false
	  },
	  {
	    "name": "Ebony Moore",
	    "candidate_type": "Regular",
	    "votes": 27,
	    "winner": false
	  }
	  ,
	  {
	    "name": "Write-In Votes",
	    "candidate_type": "Regular",
	    "votes": 15,
	    "winner": false
	  }
	
	],
	"winners": [0, 1]
      }